duniterpy/__init__.py
duniterpy/api/__init__.py
duniterpy/api/bma/__init__.py
duniterpy/api/bma/blockchain.py
duniterpy/api/bma/network.py
duniterpy/api/bma/node.py
duniterpy/api/bma/tx.py
duniterpy/api/bma/ud.py
duniterpy/api/bma/wot.py
duniterpy/api/bma/ws.py
duniterpy/api/client.py
duniterpy/api/endpoint.py
duniterpy/api/errors.py
duniterpy/api/ws2p/__init__.py
duniterpy/api/ws2p/network.py
duniterpy/api/ws2p/requests.py
duniterpy/constants.py
duniterpy/documents/__init__.py
duniterpy/documents/block.py
duniterpy/documents/block_id.py
duniterpy/documents/certification.py
duniterpy/documents/document.py
duniterpy/documents/identity.py
duniterpy/documents/membership.py
duniterpy/documents/peer.py
duniterpy/documents/revocation.py
duniterpy/documents/transaction.py
duniterpy/documents/ws2p/__init__.py
duniterpy/documents/ws2p/heads.py
duniterpy/documents/ws2p/messages.py
duniterpy/grammars/__init__.py
duniterpy/grammars/output.py
duniterpy/helpers/__init__.py
duniterpy/helpers/blockchain.py
duniterpy/helpers/money.py
duniterpy/helpers/network.py
duniterpy/helpers/ws2p.py
duniterpy/key/__init__.py
duniterpy/key/ascii_armor.py
duniterpy/key/base58.py
duniterpy/key/constants.py
duniterpy/key/crc_pubkey.py
duniterpy/key/encryption_key.py
duniterpy/key/scrypt_params.py
duniterpy/key/signing_key.py
duniterpy/key/verifying_key.py
duniterpy/py.typed
duniterpy/tools.py
examples/__init__.py
examples/create_mnemonic_wallet.py
examples/create_public_key.py
examples/listen_ws2p.py
examples/load_binary_encrypted_message.py
examples/load_binary_signed_message.py
examples/load_cleartext_ascii_armor_message.py
examples/load_credentials_file.py
examples/load_encrypted_ascii_armor_message.py
examples/load_local_blockchain.py
examples/load_scuttlebutt_file.py
examples/request_available_nodes.py
examples/request_data.py
examples/request_data_async.py
examples/request_data_elasticsearch.py
examples/request_data_graphql.py
examples/request_web_socket_block.py
examples/request_ws2p.py
duniterpy-1.2.1.dist-info/LICENSE
duniterpy-1.2.1.dist-info/METADATA
duniterpy-1.2.1.dist-info/WHEEL
duniterpy-1.2.1.dist-info/RECORD
