Metadata-Version: 2.3
Name: duniterpy
Version: 1.2.1
Summary: Python library for developers of Duniter clients
License: GPL-3.0-or-later
Keywords: g1,duniter,cryptocurrency,librecurrency,library
Author: inso
Author-email: insomniak.fr@gmail.com
Maintainer: vit, Vincent Texier
Maintainer-email: vit@free.fr
Requires-Python: >=3.9,<4.0
Classifier: Development Status :: 5 - Production/Stable
Classifier: Intended Audience :: Developers
Classifier: License :: OSI Approved :: GNU General Public License v3 or later (GPLv3+)
Classifier: Natural Language :: English
Classifier: Operating System :: OS Independent
Classifier: Programming Language :: Python :: 3
Classifier: Programming Language :: Python :: 3.9
Classifier: Programming Language :: Python :: 3.10
Classifier: Programming Language :: Python :: 3.11
Classifier: Programming Language :: Python :: 3.12
Classifier: Programming Language :: Python :: 3.13
Classifier: Topic :: Software Development :: Libraries :: Python Modules
Requires-Dist: base58 (>=2.1.1,<3.0.0)
Requires-Dist: graphql-core (>=3.2.3,<4.0.0)
Requires-Dist: jsonschema (>=4.17.3,<5.0.0)
Requires-Dist: libnacl (>=2.1.0,<3.0.0)
Requires-Dist: mnemonic (>=0.20,<0.21)
Requires-Dist: pyaes (>=1.6.1,<2.0.0)
Requires-Dist: pypeg2 (>=2.15.2,<3.0.0)
Requires-Dist: websocket-client (>=1.5.2,<2.0.0)
